{"Content-Type": "message/rfc822", "Content-Type-Override": "message/rfc822", "MboxParser-content-transfer-encoding": "quoted-printable", "MboxParser-from": "r  Mon Aug 14 11:00:02 2006", "MboxParser-mime-version": "1.0", "MboxParser-reply-to": "mrben_45@yahoo.com", "MboxParser-return-path": "<mrben_44@yahoo.com> Dear Good Friend=2C", "MboxParser-status": "RO", "MboxParser-x-mailer": "Microsoft Outlook Express 5.00.2919.6900 DM", "MboxParser-x-sieve": "CMU Sieve 2.2", "Message-From": "Mr Ben <mrben_44@yahoo.com>", "Message:From-Email": "mrben_44@yahoo.com", "Message:From-Name": "Mr Ben", "Message:Raw-Header:Content-Transfer-Encoding": "quoted-printable", "Message:Raw-Header:Content-Type": "text/plain; charset=\"us-ascii\"", "Message:Raw-Header:MIME-Version": "1.0", "Message:Raw-Header:Message-Id": "<200608141459.k7EExnlP011996@faithful.mail.UM>", "Message:Raw-Header:Reply-To": "mrben_45@yahoo.com", "Message:Raw-Header:Return-Path": "<mrben_44@yahoo.com>", "Message:Raw-Header:Status": "RO", "Message:Raw-Header:X-Mailer": "Microsoft Outlook Express 5.00.2919.6900 DM", "Message:Raw-Header:X-Sieve": "CMU Sieve 2.2", "X-TIKA:Parsed-By": ["org.apache.tika.parser.DefaultParser", "org.apache.tika.parser.mail.RFC822Parser"], "X-TIKA:content": "\n\n\n\n\n\n\n\n\n\n\n\n\n\n\n\n\n\n\n\n\n\n\n\n\n\n\n\n\n\n\n\n\n\n\nFOR  YOUR  ATTENTION  ONLY.\n\n Dear Good Friend,\r\nMy name is Mr Ben Azizi i am the branch and computer manager here in our bank.I have only written to seek your indulgence and assistance. I wish to make a transfer involving a huge.amount of base 17.5,000,000.00 {seventeen Million five hundred thousand United State Dollars}of Late Mr Mark Smith out of the bank,he died since 1995,till now the account remains dormat.I am proposing to make this transfer to a designated bank account of your choice.\r\nThus, for your indulgence and support, I propose an offer of 20% of the total amount to be yours after the transfer has been successfully concluded.\r\nYour full name and.phone number/fax is need in the first place.Kindly reply me stating your interest, and I shall furnish you with the details and necessary proceedures with which to make the transfer progress.\r\nI will give you all the vital information of the account which you will use to overcome the bank stringent test and gives you right to deposit as next of kin if you follow my instruction and directives.\r\nYours faithfully,\r\nMr Ben.Azizi\r\n\r\n\r\n\r\n\r\n\n\n", "X-TIKA:content_handler": "ToTextContentHandler", "X-TIKA:embedded_depth": "1", "X-TIKA:embedded_resource_path": "/embedded-2927", "X-TIKA:parse_time_millis": "1", "dc:creator": ["\"Mr Ben\" <mrben_44@yahoo.com>", "Mr Ben <mrben_44@yahoo.com>"], "dc:format": "text/plain; charset=\"us-ascii\"", "dc:identifier": "<200608141459.k7EExnlP011996@faithful.mail.UM>", "dc:subject": "FOR  YOUR  ATTENTION  ONLY.", "dc:title": "FOR  YOUR  ATTENTION  ONLY.", "dcterms:created": "2006-08-14T14:59:52Z"}