{"Content-Type": "message/rfc822", "Content-Type-Override": "message/rfc822", "MboxParser-content-transfer-encoding": "quoted-printable", "MboxParser-from": "r  Mon Jul  3 17:26:02 2006", "MboxParser-mime-version": "1.0", "MboxParser-reply-to": "benita_sankara2@yahoo.com", "MboxParser-return-path": "<benita_sankara2@yahoo.com>", "MboxParser-status": "O", "MboxParser-x-mailer": "Microsoft Outlook Express 5.00.2919.6900 DM", "MboxParser-x-sieve": "CMU Sieve 2.2", "Message-From": "Mrs Benita Sankara <benita_sankara2@yahoo.com>", "Message:From-Email": "benita_sankara2@yahoo.com", "Message:From-Name": "Mrs Benita Sankara", "Message:Raw-Header:Content-Transfer-Encoding": "quoted-printable", "Message:Raw-Header:Content-Type": "text/plain; charset=\"us-ascii\"", "Message:Raw-Header:MIME-Version": "1.0", "Message:Raw-Header:Message-Id": "<200607032125.k63LPoXO013827@flawless.mail.UM>", "Message:Raw-Header:Reply-To": "benita_sankara2@yahoo.com", "Message:Raw-Header:Return-Path": "<benita_sankara2@yahoo.com>", "Message:Raw-Header:Status": "O", "Message:Raw-Header:X-Mailer": "Microsoft Outlook Express 5.00.2919.6900 DM", "Message:Raw-Header:X-Sieve": "CMU Sieve 2.2", "X-TIKA:Parsed-By": ["org.apache.tika.parser.DefaultParser", "org.apache.tika.parser.mail.RFC822Parser"], "X-TIKA:content": "\n\n\n\n\n\n\n\n\n\n\n\n\n\n\n\n\n\n\n\n\n\n\n\n\n\n\n\n\n\n\n\n\n\n\nWaiting To Hear From You. \n\nDear Friend,\r\nI know that this letter might be a suprise to you but do consider it as an emergency. I am Mrs Benita sankara from Senegal, i am 43years old and i reside here with my son(ADAMS Sankara), I am here in Senegal with some amount of money $7.5million usd for investment.\r\n\r\nPlease if you are interested contact me for further clarification.\r\nThanks.\r\nMrs Benita Sankara and son Adams.\r\n\r\n\r\n\r\n\r\n\n\n", "X-TIKA:content_handler": "ToTextContentHandler", "X-TIKA:embedded_depth": "1", "X-TIKA:embedded_resource_path": "/embedded-2780", "X-TIKA:parse_time_millis": "1", "dc:creator": ["\"Mrs Benita Sankara\" <benita_sankara2@yahoo.com>", "Mrs Benita Sankara <benita_sankara2@yahoo.com>"], "dc:format": "text/plain; charset=\"us-ascii\"", "dc:identifier": "<200607032125.k63LPoXO013827@flawless.mail.UM>", "dc:subject": "Waiting To Hear From You. ", "dc:title": "Waiting To Hear From You. ", "dcterms:created": "2006-07-03T21:25:46Z"}